{
  "snapshot_id": "20260402_193003_t01hz",
  "tested_at": "2026-04-02T22:30:07.902Z",
  "tested_count": 2,
  "detail_ok_count": 2,
  "detail_fail_count": 0,
  "cache_size_before": 85,
  "cache_size_after": 87,
  "offers": [
    {
      "index": 1,
      "link": "https://clube.uol.com.br/centralpsicologia/pfm-sesses-de-terapia-por-apenas-r-90",
      "card_title": "SessГµes de terapia por apenas R$90!",
      "category": "",
      "partner_name": "Central Psicologia",
      "partner_img_url": "https://ddrxgn8ucibei.cloudfront.net/parceiros/8488a8cc5e412a2bd3c4e86078d8e9a7.png",
      "card_img_url": "https://ddrxgn8ucibei.cloudfront.net/beneficios/d544018f1f2f18f9d80331359b49423a.png",
      "detail_ok": true,
      "detail_title": "Sessões de terapia por apenas R$90!",
      "detail_html_length": 116583,
      "validity": "Benefício válido de 09/03/2026 17:12 até 31/12/2028 23:59 .",
      "has_validity": true,
      "description_preview": "Sobre o Parceiro: A Central Psicologia é uma plataforma online de divulgação que aproxima pessoas que buscam apoio psicológico de psicólogas e psicólogos independentes em todo o Brasil. Não somos clínica, consultório ou serviço de saúde próprio: nosso papel é facilitar o encontro entre quem precisa de atendimento e profissionais regularmente inscritos em seus respectivos Conselhos Regionais de Psicologia (CRPs). Benefício: Sessões de terapia pelo valor fixo de R$90,00! Regras: Valor fixo por ses",
      "has_description": true,
      "detail_img_url": "https://ddrxgn8ucibei.cloudfront.net/beneficios/d544018f1f2f18f9d80331359b49423a.png",
      "error": ""
    },
    {
      "index": 2,
      "link": "https://clube.uol.com.br/espetaculocheztoi-emseulugar/pfj-50-off-em-at-4-ingressos",
      "card_title": "50% OFF em atГ© 4 ingressos",
      "category": "PromoГ§Гµes do MГЄs",
      "partner_name": "EspetГЎculo Chez Toi - Em Seu Lugar",
      "partner_img_url": "https://ddrxgn8ucibei.cloudfront.net/parceiros/115ecb9e9fb8b7a643faae3fc21c203c.png",
      "card_img_url": "https://ddrxgn8ucibei.cloudfront.net/beneficios/ec296b77dc3a0fc397c0effe52c9b660.png",
      "detail_ok": true,
      "detail_title": "50% OFF em até 4 ingressos",
      "detail_html_length": 115218,
      "validity": "Benefício válido de 09/03/2026 15:54 até 07/06/2026 23:59 .",
      "has_validity": true,
      "description_preview": "Sobre o parceiro: Espetáculo Chez Toi – Em Seu Lugar estreia em maio na cidade de São Paulo em curta temporada com Barbara Bruno no elenco comemorando os seus 70 de idade e 55 de carreira. “Chez Toi – Em Seu Lugar” usa do realismo mágico e toques de muito humor para contar a história de Abigail (Barbara Bruno), uma mulher que vive sozinha em seu apartamento e recebe constantes visitas de sua filha Emily (Bianca Rinaldi), uma mulher com traumas do passado. Benefício: Cupom de 50% OFF em até 4 ing",
      "has_description": true,
      "detail_img_url": "https://ddrxgn8ucibei.cloudfront.net/beneficios/ec296b77dc3a0fc397c0effe52c9b660.png",
      "error": ""
    }
  ]
}